hubspot_discover/hubspot_discover/__init__.py
hubspot_discover/hubspot_discover/cli.py
hubspot_discover/hubspot_discover/discover.py
hubspot_discover/hubspot_discover/tools/config.py
hubspot_discover/hubspot_discover/tools/default.py
hubspot_discover/hubspot_discover/tools/file.py
hubspot_discover/hubspot_discover/tools/hubspot.py
hubspot_discover/hubspot_discover/tools/requests.py
hubspot_discover/hubspot_discover/tools/string.py
hubspot_discover/tests/__init__.py
hubspot_discover-1.0.0.dist-info/METADATA
hubspot_discover-1.0.0.dist-info/WHEEL
hubspot_discover-1.0.0.dist-info/entry_points.txt
hubspot_discover-1.0.0.dist-info/RECORD
